todo_cli_typer/__init__.py
todo_cli_typer/__main__.py
todo_cli_typer/cli.py
todo_cli_typer/config.py
todo_cli_typer/database.py
todo_cli_typer/models.py
todo_cli_typer/todo_cli_typer.py
todo_cli_typer/util.py
todo_cli_typer-0.6.4.dist-info/entry_points.txt
todo_cli_typer-0.6.4.dist-info/WHEEL
todo_cli_typer-0.6.4.dist-info/METADATA
todo_cli_typer-0.6.4.dist-info/RECORD
